{
    "id_match": "6a0890c586b3bc9d0d423ddd",
    "firstTurn": 0,
    "primary": 2,
    "secondaryPlayerOne": false,
    "secondaryPlayerTwo": true,
    "type": 1,
    "id": "6a0890c586b3bc9d0d423ddd",
    "scoreOne": 8,
    "scoreTwo": 12,
    "playerOneId": "623f594dc4babc7434f75c70",
    "playerTwoId": "5e447368a07d3f7c73f2bb37",
    "armyOne": "DL",
    "armyTwo": "WDG",
    "setup": {
        "deployment": "Assault at First Light",
        "primary": "Breakthrough",
        "secondaryPlayerOne": "Assassinate",
        "secondaryPlayerTwo": "Conserve our Numbers"
    }
}