{
    "id_match": "697c5b00dddfc55f24af7d05",
    "firstTurn": 0,
    "primary": 0,
    "type": 1,
    "id": "697c5b00dddfc55f24af7d05",
    "scoreOne": 17,
    "scoreTwo": 3,
    "armyOne": "OnG",
    "armyTwo": "EoS",
    "setup": {
        "deployment": "Frontline Crash",
        "primary": "Breakthrough"
    },
    "armyListOne": {
        "units": [
            {
                "name": "Orc Shaman",
                "cost": 355,
                "options": [
                    {
                        "name": "Light Troops",
                        "type": "Mount"
                    },
                    {
                        "name": "Wizard Adept",
                        "type": "Wizard Level"
                    },
                    {
                        "name": "Pyromancy",
                        "type": "Path"
                    },
                    {
                        "name": "Skull Fetish",
                        "type": "Magic Items"
                    }
                ],
                "index": 0,
                "category": "Characters"
            },
            {
                "name": "Orc Shaman",
                "cost": 310,
                "options": [
                    {
                        "name": "General",
                        "type": "Leadership"
                    },
                    {
                        "name": "Tribe Leader",
                        "type": "Other"
                    },
                    {
                        "name": "Light Troops",
                        "type": "Mount"
                    },
                    {
                        "name": "Wizard Adept",
                        "type": "Wizard Level"
                    },
                    {
                        "name": "Shamanism",
                        "type": "Path"
                    },
                    {
                        "name": "Pan of Protection Pinchin'",
                        "type": "Magic Items"
                    }
                ],
                "index": 1,
                "category": "Characters"
            },
            {
                "name": "Brood Alpha",
                "cost": 175,
                "options": [
                    {
                        "name": "Light Troops",
                        "type": "Mount"
                    },
                    {
                        "name": "Binding Scroll",
                        "type": "Magic Items"
                    },
                    {
                        "name": "Battle Standard Bearer",
                        "type": "Leadership"
                    },
                    {
                        "name": "Shield",
                        "type": "Other"
                    }
                ],
                "index": 0,
                "category": "Characters"
            },
            {
                "name": "Feral Orc Marauders",
                "cost": 250,
                "options": [
                    {
                        "name": "Musician",
                        "type": "Command Group"
                    },
                    {
                        "name": "Standard Bearer",
                        "type": "Command Group"
                    }
                ],
                "index": 0,
                "models": 10,
                "category": "Core"
            },
            {
                "name": "Feral Orcs",
                "cost": 250,
                "options": [
                    {
                        "name": "Sheltering Standard",
                        "type": "Magic Items"
                    },
                    {
                        "name": "Standard Bearer",
                        "type": "Command Group"
                    }
                ],
                "index": 0,
                "models": 25,
                "category": "Core"
            },
            {
                "name": "Feral Orcs",
                "cost": 250,
                "options": [
                    {
                        "name": "Sheltering Standard",
                        "type": "Magic Items"
                    },
                    {
                        "name": "Standard Bearer",
                        "type": "Command Group"
                    }
                ],
                "index": 1,
                "models": 25,
                "category": "Core"
            },
            {
                "name": "Feral Orcs",
                "cost": 250,
                "options": [
                    {
                        "name": "Banner of Courage",
                        "type": "Magic Items"
                    },
                    {
                        "name": "Standard Bearer",
                        "type": "Command Group"
                    }
                ],
                "index": 2,
                "models": 25,
                "category": "Core"
            },
            {
                "name": "Iron Orcs",
                "cost": 467,
                "options": [
                    {
                        "name": "Headbashers",
                        "type": "Other"
                    },
                    {
                        "name": "Standard Bearer",
                        "type": "Command Group"
                    }
                ],
                "index": 0,
                "models": 22,
                "category": "Special"
            },
            {
                "name": "Great Green Idol",
                "cost": 400,
                "options": [],
                "index": 0,
                "category": "Special"
            },
            {
                "name": "Giant",
                "cost": 290,
                "options": [
                    {
                        "name": "Giant Club",
                        "type": "Other"
                    }
                ],
                "index": 0,
                "category": "Special"
            },
            {
                "name": "Giant",
                "cost": 290,
                "options": [
                    {
                        "name": "Giant Club",
                        "type": "Other"
                    }
                ],
                "index": 1,
                "category": "Special"
            },
            {
                "name": "Goblin Artillery",
                "cost": 190,
                "options": [
                    {
                        "name": "Git Launcher",
                        "type": "Artillery Weapons"
                    }
                ],
                "index": 0,
                "category": "Special"
            },
            {
                "name": "Gogtuk Neophytes",
                "cost": 180,
                "options": [
                    {
                        "name": "Standard Bearer",
                        "type": "Command Group"
                    }
                ],
                "index": 0,
                "models": 10,
                "category": "Special"
            },
            {
                "name": "Gnashers",
                "cost": 170,
                "options": [
                    {
                        "name": "Herd",
                        "type": "Other"
                    }
                ],
                "index": 0,
                "models": 15,
                "category": "Special"
            },
            {
                "name": "Gnashers",
                "cost": 170,
                "options": [
                    {
                        "name": "Herd",
                        "type": "Other"
                    }
                ],
                "index": 1,
                "models": 15,
                "category": "Special"
            }
        ],
        "pointsPerCategory": {
            "Characters": 840,
            "Core": 1000,
            "Special": 2157,
            "Total": 3997
        },
        "magicalness": 11,
        "modelCount": {
            "characters": 3,
            "height0": 0,
            "height1": 137,
            "height2": 11,
            "height3": 0,
            "height4": 0,
            "height5": 3,
            "total": 154
        },
        "unitCount": {
            "characters": 3,
            "singleModel": 4,
            "rankAndFile": 8,
            "total": 15
        }
    },
    "armyListTwo": {
        "units": [
            {
                "name": "Battlefield Wizard",
                "cost": 420,
                "options": [
                    {
                        "name": "Arcane Engine",
                        "type": "Mount"
                    },
                    {
                        "name": "Wizard Adept",
                        "type": "Wizard Level"
                    },
                    {
                        "name": "Cosmology",
                        "type": "Path"
                    },
                    {
                        "name": "Spell Scroll",
                        "type": "Magic Items"
                    }
                ],
                "index": 0,
                "category": "Characters"
            },
            {
                "name": "Battlefield Wizard",
                "cost": 250,
                "options": [
                    {
                        "name": "Light Troops",
                        "type": "Mount"
                    },
                    {
                        "name": "Wizard Adept",
                        "type": "Wizard Level"
                    },
                    {
                        "name": "Divination",
                        "type": "Path"
                    }
                ],
                "index": 1,
                "category": "Characters"
            },
            {
                "name": "Prelate",
                "cost": 250,
                "options": [
                    {
                        "name": "General",
                        "type": "Leadership"
                    },
                    {
                        "name": "Light Troops",
                        "type": "Mount"
                    },
                    {
                        "name": "Imperial Seal",
                        "type": "Magic Items"
                    },
                    {
                        "name": "Giant Slayer",
                        "type": "Magic Items"
                    },
                    {
                        "name": "Shield",
                        "type": "Other"
                    }
                ],
                "index": 0,
                "category": "Characters"
            },
            {
                "name": "Marshal",
                "cost": 250,
                "options": [
                    {
                        "name": "Great Griffon",
                        "type": "Mount"
                    },
                    {
                        "name": "Solitary",
                        "type": "Leadership"
                    },
                    {
                        "name": "Halberd",
                        "type": "Melee Weapons"
                    },
                    {
                        "name": "Brace of Pistols",
                        "type": "Other"
                    }
                ],
                "index": 0,
                "category": "Characters"
            },
            {
                "name": "Marshal",
                "cost": 250,
                "options": [
                    {
                        "name": "Great Griffon",
                        "type": "Mount"
                    },
                    {
                        "name": "Solitary",
                        "type": "Leadership"
                    },
                    {
                        "name": "Halberd",
                        "type": "Melee Weapons"
                    },
                    {
                        "name": "Brace of Pistols",
                        "type": "Other"
                    }
                ],
                "index": 1,
                "category": "Characters"
            },
            {
                "name": "Marshal",
                "cost": 180,
                "options": [
                    {
                        "name": "Light Troops",
                        "type": "Mount"
                    },
                    {
                        "name": "Blacksteel",
                        "type": "Magic Items"
                    },
                    {
                        "name": "Ullor's Horn",
                        "type": "Magic Items"
                    },
                    {
                        "name": "Shield",
                        "type": "Other"
                    },
                    {
                        "name": "Battle Standard Bearer and Imperial Authority",
                        "type": "Other"
                    }
                ],
                "index": 2,
                "category": "Characters"
            },
            {
                "name": "State Infantry",
                "cost": 547,
                "options": [
                    {
                        "name": "War College Banner",
                        "type": "Magic Items"
                    },
                    {
                        "name": "Spear",
                        "type": "Melee Weapons"
                    },
                    {
                        "name": "Standard Bearer",
                        "type": "Command Group"
                    }
                ],
                "index": 0,
                "models": 47,
                "category": "Core"
            },
            {
                "name": "State Marksmen",
                "cost": 165,
                "options": [
                    {
                        "name": "Standard Bearer",
                        "type": "Command Group"
                    },
                    {
                        "name": "Handgun",
                        "type": "Shooting Weapons"
                    }
                ],
                "index": 0,
                "models": 12,
                "category": "Core"
            },
            {
                "name": "State Detachment",
                "cost": 145,
                "options": [
                    {
                        "name": "Halberd",
                        "type": "Melee Weapons"
                    },
                    {
                        "name": "Standard Bearer",
                        "type": "Command Group"
                    }
                ],
                "index": 0,
                "models": 15,
                "category": "Core"
            },
            {
                "name": "State Detachment",
                "cost": 145,
                "options": [
                    {
                        "name": "Halberd",
                        "type": "Melee Weapons"
                    },
                    {
                        "name": "Standard Bearer",
                        "type": "Command Group"
                    }
                ],
                "index": 1,
                "models": 15,
                "category": "Core"
            },
            {
                "name": "Knights of the Sun Griffon",
                "cost": 445,
                "options": [
                    {
                        "name": "Lance",
                        "type": "Melee Weapons"
                    },
                    {
                        "name": "Flaming Standard",
                        "type": "Magic Items"
                    },
                    {
                        "name": "Standard Bearer",
                        "type": "Command Group"
                    }
                ],
                "index": 0,
                "models": 5,
                "category": "Special"
            },
            {
                "name": "Knights of the Sun Griffon",
                "cost": 405,
                "options": [
                    {
                        "name": "Lance",
                        "type": "Melee Weapons"
                    },
                    {
                        "name": "Standard Bearer",
                        "type": "Command Group"
                    }
                ],
                "index": 1,
                "models": 5,
                "category": "Special"
            },
            {
                "name": "Imperial Rangers",
                "cost": 108,
                "options": [],
                "index": 0,
                "models": 9,
                "category": "Special"
            },
            {
                "name": "Steam Tank",
                "cost": 440,
                "options": [],
                "index": 0,
                "category": "Sunna's Fury"
            }
        ],
        "pointsPerCategory": {
            "Characters": 1600,
            "Core": 1002,
            "Special": 958,
            "Total": 4000
        },
        "magicalness": 11,
        "modelCount": {
            "characters": 6,
            "height0": 0,
            "height1": 98,
            "height2": 0,
            "height3": 10,
            "height4": 0,
            "height5": 1,
            "total": 115
        },
        "unitCount": {
            "characters": 6,
            "singleModel": 1,
            "rankAndFile": 7,
            "total": 14
        }
    }
}