{
    "id_match": "692c478b8a308fc2323a919b",
    "firstTurn": 1,
    "primary": 0,
    "type": 1,
    "id": "692c478b8a308fc2323a919b",
    "scoreOne": 20,
    "scoreTwo": 0,
    "armyOne": "WDG",
    "armyTwo": "DE",
    "setup": {
        "map": "Dormant Caldera",
        "deployment": "Bottleneck"
    },
    "armyListOne": {
        "units": [
            {
                "name": "Chosen Lord",
                "cost": 635,
                "options": [
                    {
                        "name": "General",
                        "type": "Leadership"
                    },
                    {
                        "name": "Chimera",
                        "type": "Mount"
                    },
                    {
                        "name": "Paired Weapons",
                        "type": "Melee Weapons"
                    },
                    {
                        "name": "Symbol of Slaughter",
                        "type": "Magic Items"
                    },
                    {
                        "name": "Talisman of Shielding",
                        "type": "Magic Items"
                    },
                    {
                        "name": "Wyrd Stone",
                        "type": "Magic Items"
                    },
                    {
                        "name": "Gluttony",
                        "type": "Favour"
                    },
                    {
                        "name": "Luck of the Dark Gods",
                        "type": "Gifts of the Dark Gods"
                    }
                ],
                "index": 0,
                "category": "Characters"
            },
            {
                "name": "Sorcerer",
                "cost": 540,
                "options": [
                    {
                        "name": "Light Troops",
                        "type": "Mount"
                    },
                    {
                        "name": "Basalt Infusion",
                        "type": "Magic Items"
                    },
                    {
                        "name": "Dark Familiar",
                        "type": "Magic Items"
                    },
                    {
                        "name": "Wizard Master",
                        "type": "Wizard Level"
                    },
                    {
                        "name": "Occultism",
                        "type": "Path"
                    }
                ],
                "index": 0,
                "category": "Characters"
            },
            {
                "name": "Warriors",
                "cost": 410,
                "options": [
                    {
                        "name": "Zealots' Banner",
                        "type": "Magic Items"
                    },
                    {
                        "name": "Paired Weapons",
                        "type": "Melee Weapons"
                    },
                    {
                        "name": "Standard Bearer",
                        "type": "Command Group"
                    }
                ],
                "index": 0,
                "models": 17,
                "category": "Core"
            },
            {
                "name": "Warriors",
                "cost": 390,
                "options": [
                    {
                        "name": "Zealots' Banner",
                        "type": "Magic Items"
                    },
                    {
                        "name": "Paired Weapons",
                        "type": "Melee Weapons"
                    },
                    {
                        "name": "Standard Bearer",
                        "type": "Command Group"
                    }
                ],
                "index": 1,
                "models": 16,
                "category": "Core"
            },
            {
                "name": "Chosen",
                "cost": 600,
                "options": [
                    {
                        "name": "Aether Icon",
                        "type": "Magic Items"
                    },
                    {
                        "name": "Paired Weapons",
                        "type": "Melee Weapons"
                    },
                    {
                        "name": "Greed",
                        "type": "Favour"
                    },
                    {
                        "name": "Standard Bearer",
                        "type": "Command Group"
                    }
                ],
                "index": 0,
                "models": 10,
                "category": "Special"
            },
            {
                "name": "Chosen Knights",
                "cost": 570,
                "options": [
                    {
                        "name": "Icon of the Infinite",
                        "type": "Magic Items"
                    },
                    {
                        "name": "Wrath",
                        "type": "Favour"
                    },
                    {
                        "name": "Standard Bearer",
                        "type": "Command Group"
                    }
                ],
                "index": 0,
                "models": 4,
                "category": "Special"
            },
            {
                "name": "Chosen Knights",
                "cost": 530,
                "options": [
                    {
                        "name": "Wrath",
                        "type": "Favour"
                    },
                    {
                        "name": "Standard Bearer",
                        "type": "Command Group"
                    }
                ],
                "index": 1,
                "models": 4,
                "category": "Special"
            },
            {
                "name": "Battleshrine",
                "cost": 320,
                "options": [],
                "index": 0,
                "category": "Special"
            }
        ],
        "pointsPerCategory": {
            "Characters": 1175,
            "Core": 1000,
            "Special": 2020,
            "Total": 3995
        },
        "magicalness": 8
    },
    "armyListTwo": {
        "units": [
            {
                "name": "Temple Exarch",
                "cost": 390,
                "options": [
                    {
                        "name": "General",
                        "type": "Leadership"
                    },
                    {
                        "name": "Wizard Adept",
                        "type": "Wizard Level"
                    },
                    {
                        "name": "Divination",
                        "type": "Path"
                    },
                    {
                        "name": "Great Weapon and Elven Finesse",
                        "type": "Melee Weapons"
                    },
                    {
                        "name": "Scroll of Power",
                        "type": "Magic Items"
                    },
                    {
                        "name": "Ceinran's Scales",
                        "type": "Magic Items"
                    }
                ],
                "index": 0,
                "category": "Characters"
            },
            {
                "name": "Silexian Spears",
                "cost": 320,
                "options": [
                    {
                        "name": "Caedhren's Pennon",
                        "type": "Magic Items"
                    },
                    {
                        "name": "Standard Bearer",
                        "type": "Command Group"
                    }
                ],
                "index": 0,
                "models": 20,
                "category": "Core"
            },
            {
                "name": "Silexian Spears",
                "cost": 320,
                "options": [
                    {
                        "name": "Caedhren's Pennon",
                        "type": "Magic Items"
                    },
                    {
                        "name": "Standard Bearer",
                        "type": "Command Group"
                    }
                ],
                "index": 1,
                "models": 20,
                "category": "Core"
            },
            {
                "name": "Corsairs",
                "cost": 185,
                "options": [
                    {
                        "name": "Repeater Handbow",
                        "type": "Shooting Weapons"
                    }
                ],
                "index": 0,
                "models": 10,
                "category": "Core"
            },
            {
                "name": "Corsairs",
                "cost": 185,
                "options": [
                    {
                        "name": "Repeater Handbow",
                        "type": "Shooting Weapons"
                    }
                ],
                "index": 1,
                "models": 10,
                "category": "Core"
            },
            {
                "name": "Gorgons",
                "cost": 410,
                "options": [
                    {
                        "name": "Paired Weapons",
                        "type": "Melee Weapons"
                    }
                ],
                "index": 0,
                "models": 4,
                "category": "Special"
            },
            {
                "name": "Temple Militants",
                "cost": 368,
                "options": [
                    {
                        "name": "Banner of Urlain",
                        "type": "Magic Items"
                    },
                    {
                        "name": "Standard Bearer",
                        "type": "Command Group"
                    },
                    {
                        "name": "Dancers of Yema",
                        "type": "Other"
                    }
                ],
                "index": 0,
                "models": 14,
                "category": "Special"
            },
            {
                "name": "Black Cloaks",
                "cost": 330,
                "options": [
                    {
                        "name": "Repeater Handbow and Poison Attacks",
                        "type": "Shooting Weapons"
                    },
                    {
                        "name": "Covert Operatives",
                        "type": "Other"
                    }
                ],
                "index": 0,
                "models": 10,
                "category": "Special"
            },
            {
                "name": "Shadow Riders",
                "cost": 270,
                "options": [
                    {
                        "name": "Light Lance and Repeater Crossbow",
                        "type": "Shooting Weapons"
                    }
                ],
                "index": 0,
                "models": 10,
                "category": "Special"
            },
            {
                "name": "Judicators",
                "cost": 260,
                "options": [
                    {
                        "name": "Banner of Urlain",
                        "type": "Magic Items"
                    },
                    {
                        "name": "Standard Bearer",
                        "type": "Command Group"
                    }
                ],
                "index": 0,
                "models": 10,
                "category": "Special"
            },
            {
                "name": "Judicators",
                "cost": 260,
                "options": [
                    {
                        "name": "Banner of Urlain",
                        "type": "Magic Items"
                    },
                    {
                        "name": "Standard Bearer",
                        "type": "Command Group"
                    }
                ],
                "index": 1,
                "models": 10,
                "category": "Special"
            },
            {
                "name": "Divine Altar",
                "cost": 240,
                "options": [
                    {
                        "name": "Altar of Nabh",
                        "type": "Other"
                    }
                ],
                "index": 0,
                "category": "Special"
            },
            {
                "name": "Obsidian Guard",
                "cost": 230,
                "options": [
                    {
                        "name": "Standard Bearer",
                        "type": "Command Group"
                    }
                ],
                "index": 0,
                "models": 10,
                "category": "Special"
            },
            {
                "name": "Obsidian Guard",
                "cost": 230,
                "options": [
                    {
                        "name": "Standard Bearer",
                        "type": "Command Group"
                    }
                ],
                "index": 1,
                "models": 10,
                "category": "Special"
            }
        ],
        "pointsPerCategory": {
            "Characters": 390,
            "Core": 1010,
            "Special": 2598,
            "Total": 3998
        },
        "magicalness": 5
    }
}