{
    "id_match": "67ae3e73d1ecbdf2c7f2b683",
    "firstTurn": 0,
    "primary": 1,
    "secondaryPlayerOne": false,
    "secondaryPlayerTwo": false,
    "type": 1,
    "id": "67ae3e73d1ecbdf2c7f2b683",
    "scoreOne": 5,
    "scoreTwo": 15,
    "playerOneId": "5df1039de541441ab3997c43",
    "playerTwoId": "6190d76bc77ccb1989c33c7c",
    "armyOne": "DE",
    "armyTwo": "DE",
    "setup": {
        "deployment": "Bottleneck",
        "primary": "Hidden Agendas"
    },
    "armyListOne": {
        "units": [
            {
                "name": "Sanctioned Warlock",
                "cost": 480,
                "options": [
                    {
                        "name": "Recruiting Officer",
                        "type": "Specialist Skill"
                    },
                    {
                        "name": "Light Troops",
                        "type": "Mount"
                    },
                    {
                        "name": "Wizard Master",
                        "type": "Wizard Level"
                    },
                    {
                        "name": "Evocation",
                        "type": "Path"
                    },
                    {
                        "name": "Ring of the Obsidian Thrones",
                        "type": "Magic Items"
                    }
                ],
                "index": 0,
                "category": "Characters"
            },
            {
                "name": "Dread Prince",
                "cost": 440,
                "options": [
                    {
                        "name": "General",
                        "type": "Leadership"
                    },
                    {
                        "name": "Battleline Hero",
                        "type": "Specialist Skill"
                    },
                    {
                        "name": "Light Troops",
                        "type": "Mount"
                    },
                    {
                        "name": "Paired Weapons",
                        "type": "Melee Weapons"
                    },
                    {
                        "name": "Lacerating Touch",
                        "type": "Magic Items"
                    },
                    {
                        "name": "Seal of the Republic",
                        "type": "Magic Items"
                    },
                    {
                        "name": "Beastmaster's Vial",
                        "type": "Magic Items"
                    },
                    {
                        "name": "Moithir's Mirror",
                        "type": "Magic Items"
                    },
                    {
                        "name": "Academy Commander",
                        "type": "Other"
                    }
                ],
                "index": 0,
                "category": "Characters"
            },
            {
                "name": "Silexian Spears",
                "cost": 436,
                "options": [
                    {
                        "name": "Standard Bearer",
                        "type": "Command Group"
                    },
                    {
                        "name": "Flaming Standard",
                        "type": "Magic Items"
                    },
                    {
                        "name": "Musician",
                        "type": "Command Group"
                    }
                ],
                "index": 0,
                "models": 29,
                "category": "Core"
            },
            {
                "name": "Silexian Auxiliaries",
                "cost": 220,
                "options": [
                    {
                        "name": "Standard Bearer",
                        "type": "Command Group"
                    }
                ],
                "index": 0,
                "models": 10,
                "category": "Core"
            },
            {
                "name": "Silexian Auxiliaries",
                "cost": 220,
                "options": [
                    {
                        "name": "Standard Bearer",
                        "type": "Command Group"
                    }
                ],
                "index": 1,
                "models": 10,
                "category": "Core"
            },
            {
                "name": "Corsairs",
                "cost": 185,
                "options": [
                    {
                        "name": "Repeater Handbow",
                        "type": "Shooting Weapons"
                    }
                ],
                "index": 0,
                "models": 10,
                "category": "Core"
            },
            {
                "name": "Thunder Pack",
                "cost": 490,
                "options": [],
                "index": 0,
                "models": 6,
                "category": "Special"
            },
            {
                "name": "Gorgons",
                "cost": 410,
                "options": [
                    {
                        "name": "Paired Weapons",
                        "type": "Melee Weapons"
                    }
                ],
                "index": 0,
                "models": 4,
                "category": "Special"
            },
            {
                "name": "Temple Militants",
                "cost": 390,
                "options": [
                    {
                        "name": "Standard Bearer",
                        "type": "Command Group"
                    },
                    {
                        "name": "Banner of Urlain",
                        "type": "Magic Items"
                    },
                    {
                        "name": "Dancers of Yema",
                        "type": "Other"
                    }
                ],
                "index": 0,
                "models": 15,
                "category": "Special"
            },
            {
                "name": "Dread Acolytes",
                "cost": 242,
                "options": [
                    {
                        "name": "Temple Acolytes",
                        "type": "Other"
                    }
                ],
                "index": 0,
                "models": 6,
                "category": "Special"
            },
            {
                "name": "Dread Acolytes",
                "cost": 242,
                "options": [
                    {
                        "name": "Temple Acolytes",
                        "type": "Other"
                    }
                ],
                "index": 1,
                "models": 6,
                "category": "Special"
            },
            {
                "name": "Divine Altar",
                "cost": 240,
                "options": [
                    {
                        "name": "Altar of Nabh",
                        "type": "Other"
                    }
                ],
                "index": 0,
                "category": "Special"
            }
        ],
        "pointsPerCategory": {
            "Characters": 920,
            "Core": 1061,
            "Special": 2014,
            "Total": 3995
        },
        "magicalness": 7,
        "modelCount": {
            "characters": 2,
            "height0": 0,
            "height1": 74,
            "height2": 12,
            "height3": 10,
            "height4": 0,
            "height5": 1,
            "total": 99
        },
        "unitCount": {
            "characters": 2,
            "singleModel": 1,
            "rankAndFile": 9,
            "total": 12
        }
    },
    "armyListTwo": {
        "units": [
            {
                "name": "Temple Exarch",
                "cost": 390,
                "options": [
                    {
                        "name": "Wizard Adept",
                        "type": "Wizard Level"
                    },
                    {
                        "name": "Alchemy",
                        "type": "Path"
                    },
                    {
                        "name": "Seal of the Republic",
                        "type": "Magic Items"
                    },
                    {
                        "name": "Shield Breaker",
                        "type": "Magic Items"
                    },
                    {
                        "name": "Paired Weapons",
                        "type": "Melee Weapons"
                    }
                ],
                "index": 0,
                "category": "Characters"
            },
            {
                "name": "Sanctioned Warlock",
                "cost": 330,
                "options": [
                    {
                        "name": "General",
                        "type": "Leadership"
                    },
                    {
                        "name": "Wizard Adept",
                        "type": "Wizard Level"
                    },
                    {
                        "name": "Ring of the Obsidian Thrones",
                        "type": "Magic Items"
                    },
                    {
                        "name": "Light Troops",
                        "type": "Mount"
                    },
                    {
                        "name": "Cosmology",
                        "type": "Path"
                    }
                ],
                "index": 0,
                "category": "Characters"
            },
            {
                "name": "Silexian Officer",
                "cost": 255,
                "options": [
                    {
                        "name": "Battle Standard Bearer",
                        "type": "Leadership"
                    },
                    {
                        "name": "Aether Icon",
                        "type": "Magic Items"
                    },
                    {
                        "name": "Ceinran's Scales",
                        "type": "Magic Items"
                    },
                    {
                        "name": "Light Troops",
                        "type": "Mount"
                    },
                    {
                        "name": "Shield",
                        "type": "Other"
                    },
                    {
                        "name": "Wild Warding",
                        "type": "Magic Items"
                    }
                ],
                "index": 0,
                "category": "Characters"
            },
            {
                "name": "Silent Assassin",
                "cost": 130,
                "options": [],
                "index": 0,
                "category": "Characters"
            },
            {
                "name": "Silent Assassin",
                "cost": 130,
                "options": [],
                "index": 1,
                "category": "Characters"
            },
            {
                "name": "Silexian Spears",
                "cost": 465,
                "options": [
                    {
                        "name": "Stalker's Standard",
                        "type": "Magic Items"
                    },
                    {
                        "name": "Standard Bearer",
                        "type": "Command Group"
                    },
                    {
                        "name": "Musician",
                        "type": "Command Group"
                    }
                ],
                "index": 0,
                "models": 30,
                "category": "Core"
            },
            {
                "name": "Temple Militants",
                "cost": 352,
                "options": [
                    {
                        "name": "Standard Bearer",
                        "type": "Command Group"
                    },
                    {
                        "name": "Musician",
                        "type": "Command Group"
                    }
                ],
                "index": 0,
                "models": 23,
                "category": "Core"
            },
            {
                "name": "Corsairs",
                "cost": 185,
                "options": [
                    {
                        "name": "Repeater Handbow",
                        "type": "Shooting Weapons"
                    }
                ],
                "index": 0,
                "models": 10,
                "category": "Core"
            },
            {
                "name": "Obsidian Guard",
                "cost": 500,
                "options": [
                    {
                        "name": "Aether Icon",
                        "type": "Magic Items"
                    },
                    {
                        "name": "Standard Bearer",
                        "type": "Command Group"
                    }
                ],
                "index": 0,
                "models": 23,
                "category": "Special"
            },
            {
                "name": "Shadow Riders",
                "cost": 270,
                "options": [
                    {
                        "name": "Light Lance and Repeater Crossbow",
                        "type": "Shooting Weapons"
                    }
                ],
                "index": 0,
                "models": 10,
                "category": "Special"
            },
            {
                "name": "Shadow Riders",
                "cost": 270,
                "options": [
                    {
                        "name": "Light Lance and Repeater Crossbow",
                        "type": "Shooting Weapons"
                    }
                ],
                "index": 1,
                "models": 10,
                "category": "Special"
            },
            {
                "name": "Gorgons",
                "cost": 210,
                "options": [
                    {
                        "name": "Paired Weapons",
                        "type": "Melee Weapons"
                    }
                ],
                "index": 0,
                "models": 2,
                "category": "Special"
            },
            {
                "name": "Harpies",
                "cost": 140,
                "options": [],
                "index": 0,
                "models": 5,
                "category": "Special"
            },
            {
                "name": "Harpies",
                "cost": 140,
                "options": [],
                "index": 1,
                "models": 5,
                "category": "Special"
            },
            {
                "name": "Mist Leviathan",
                "cost": 230,
                "options": [],
                "index": 0,
                "category": "The Menagerie"
            }
        ],
        "pointsPerCategory": {
            "Characters": 1235,
            "Core": 1002,
            "Special": 1530,
            "Total": 3997
        },
        "magicalness": 9,
        "modelCount": {
            "characters": 5,
            "height0": 0,
            "height1": 96,
            "height2": 20,
            "height3": 2,
            "height4": 0,
            "height5": 1,
            "total": 124
        },
        "unitCount": {
            "characters": 5,
            "singleModel": 1,
            "rankAndFile": 9,
            "total": 15
        }
    }
}