{
    "id_match": "6962905a7bedb8a14fd2ed89",
    "firstTurn": 0,
    "primary": 1,
    "type": 1,
    "id": "6962905a7bedb8a14fd2ed89",
    "scoreOne": 2,
    "scoreTwo": 18,
    "armyOne": "DL",
    "armyTwo": "WDG",
    "setup": {
        "map": "Vetia 2",
        "deployment": "Frontline Crash",
        "primary": "Secure Targets"
    },
    "armyListOne": {
        "units": [
            {
                "name": "Vanadra's Scourge",
                "cost": 610,
                "options": [
                    {
                        "name": "Incendiary Ichor",
                        "type": "Manifestations"
                    }
                ],
                "index": 0,
                "category": "Characters"
            },
            {
                "name": "Kuulima's Deceiver",
                "cost": 440,
                "options": [
                    {
                        "name": "Wizard Conclave",
                        "type": "Wizard Level"
                    },
                    {
                        "name": "Piercing Spike",
                        "type": "Manifestations"
                    },
                    {
                        "name": "Guiding Piercing Spike",
                        "type": "Other"
                    }
                ],
                "index": 0,
                "category": "Characters"
            },
            {
                "name": "Succubi",
                "cost": 440,
                "options": [
                    {
                        "name": "Standard Bearer",
                        "type": "Command Group"
                    }
                ],
                "index": 0,
                "models": 20,
                "category": "Core"
            },
            {
                "name": "Lemures",
                "cost": 333,
                "options": [
                    {
                        "name": "Standard Bearer",
                        "type": "Command Group"
                    }
                ],
                "index": 0,
                "models": 19,
                "category": "Core"
            },
            {
                "name": "Imps",
                "cost": 230,
                "options": [
                    {
                        "name": "Standard Bearer",
                        "type": "Command Group"
                    },
                    {
                        "name": "Firestarter - Spear of Infinity",
                        "type": "Other"
                    }
                ],
                "index": 0,
                "models": 10,
                "category": "Core"
            },
            {
                "name": "Hoarders",
                "cost": 440,
                "options": [
                    {
                        "name": "Standard Bearer",
                        "type": "Command Group"
                    }
                ],
                "index": 0,
                "models": 5,
                "category": "Special"
            },
            {
                "name": "Clawed Fiends",
                "cost": 445,
                "options": [
                    {
                        "name": "Incendiary Ichor",
                        "type": "Manifestations"
                    },
                    {
                        "name": "Standard Bearer",
                        "type": "Command Group"
                    }
                ],
                "index": 0,
                "models": 5,
                "category": "Special"
            },
            {
                "name": "Clawed Fiends",
                "cost": 250,
                "options": [
                    {
                        "name": "Standard Bearer",
                        "type": "Command Group"
                    }
                ],
                "index": 1,
                "models": 3,
                "category": "Special"
            },
            {
                "name": "Threshing Engine",
                "cost": 310,
                "options": [],
                "index": 0,
                "models": 2,
                "category": "Special"
            },
            {
                "name": "Hellhounds",
                "cost": 150,
                "options": [],
                "index": 0,
                "models": 5,
                "category": "Special"
            },
            {
                "name": "Veil Serpents",
                "cost": 350,
                "options": [
                    {
                        "name": "Wizard Conclave",
                        "type": "Wizard Level"
                    }
                ],
                "index": 0,
                "models": 3,
                "category": "Aves"
            }
        ],
        "pointsPerCategory": {
            "Characters": 1050,
            "Core": 1003,
            "Special": 1595,
            "Total": 3998
        },
        "magicalness": null,
        "modelCount": {
            "characters": 2,
            "height0": 0,
            "height1": 49,
            "height2": 5,
            "height3": 16,
            "height4": 2,
            "height5": 0,
            "total": 74
        },
        "unitCount": {
            "characters": 2,
            "singleModel": 0,
            "rankAndFile": 9,
            "total": 11
        }
    }
}