{
    "id_match": "67bb4b090e2727d3f4c0c3a7",
    "firstTurn": 0,
    "primary": 0,
    "secondaryPlayerOne": false,
    "secondaryPlayerTwo": false,
    "type": 1,
    "id": "67bb4b090e2727d3f4c0c3a7",
    "scoreOne": 20,
    "scoreTwo": 0,
    "playerOneId": "5de7603e29951610d11f74ef",
    "playerTwoId": "607023c034788760c8528c5a",
    "armyOne": "KoE",
    "armyTwo": "DE",
    "setup": {
        "deployment": "Cornerstone",
        "primary": "Breakthrough"
    },
    "armyListOne": {
        "units": [
            {
                "name": "Paladin",
                "cost": 450,
                "options": [
                    {
                        "name": "Hippogriff",
                        "type": "Mount"
                    },
                    {
                        "name": "Paired Weapons",
                        "type": "Melee Weapons"
                    },
                    {
                        "name": "Hero's Heart",
                        "type": "Magic Items"
                    }
                ],
                "index": 0,
                "category": "Characters"
            },
            {
                "name": "Damsel",
                "cost": 370,
                "options": [
                    {
                        "name": "General",
                        "type": "Leadership"
                    },
                    {
                        "name": "Destrier",
                        "type": "Mount"
                    },
                    {
                        "name": "Talisman of the Void",
                        "type": "Magic Items"
                    },
                    {
                        "name": "Wizard Adept",
                        "type": "Wizard Level"
                    },
                    {
                        "name": "Divination",
                        "type": "Path"
                    }
                ],
                "index": 0,
                "category": "Characters"
            },
            {
                "name": "Duke",
                "cost": 335,
                "options": [
                    {
                        "name": "Destrier",
                        "type": "Mount"
                    },
                    {
                        "name": "Fortress of Faith",
                        "type": "Magic Items"
                    },
                    {
                        "name": "Battle Standard Bearer",
                        "type": "Leadership"
                    },
                    {
                        "name": "Aether Icon",
                        "type": "Magic Items"
                    },
                    {
                        "name": "Generosity",
                        "type": "Knightly Principle"
                    }
                ],
                "index": 0,
                "category": "Characters"
            },
            {
                "name": "Knights of the Realm",
                "cost": 575,
                "options": [
                    {
                        "name": "Stalker's Standard",
                        "type": "Magic Items"
                    },
                    {
                        "name": "Solemn Oath",
                        "type": "Other"
                    },
                    {
                        "name": "Standard Bearer",
                        "type": "Command Group"
                    },
                    {
                        "name": "Knight Banneret",
                        "type": "Command Group"
                    }
                ],
                "index": 0,
                "models": 10,
                "category": "Core"
            },
            {
                "name": "Knights of the Realm",
                "cost": 450,
                "options": [
                    {
                        "name": "Relic Shroud",
                        "type": "Magic Items"
                    },
                    {
                        "name": "Solemn Oath",
                        "type": "Other"
                    },
                    {
                        "name": "Musician",
                        "type": "Command Group"
                    },
                    {
                        "name": "Standard Bearer",
                        "type": "Command Group"
                    },
                    {
                        "name": "Knight Banneret",
                        "type": "Command Group"
                    }
                ],
                "index": 1,
                "models": 9,
                "category": "Core"
            },
            {
                "name": "Knights of the Quest",
                "cost": 530,
                "options": [
                    {
                        "name": "Musician",
                        "type": "Command Group"
                    },
                    {
                        "name": "Standard Bearer",
                        "type": "Command Group"
                    },
                    {
                        "name": "Knight Banneret",
                        "type": "Command Group"
                    }
                ],
                "index": 0,
                "models": 8,
                "category": "Special"
            },
            {
                "name": "Men-at-Arms",
                "cost": 475,
                "options": [
                    {
                        "name": "Stalker's Standard",
                        "type": "Magic Items"
                    },
                    {
                        "name": "Musician",
                        "type": "Command Group"
                    },
                    {
                        "name": "Standard Bearer",
                        "type": "Command Group"
                    },
                    {
                        "name": "Castle Guard",
                        "type": "Other"
                    }
                ],
                "index": 0,
                "models": 30,
                "category": "Special"
            },
            {
                "name": "Sky Heralds",
                "cost": 210,
                "options": [
                    {
                        "name": "Light Lance",
                        "type": "Melee Weapons"
                    }
                ],
                "index": 0,
                "models": 3,
                "category": "Special"
            },
            {
                "name": "Sacred Reliquary",
                "cost": 180,
                "options": [],
                "index": 0,
                "category": "Special"
            },
            {
                "name": "The Lady's Courtier",
                "cost": 425,
                "options": [
                    {
                        "name": "Courtier of the Dusk",
                        "type": "Other"
                    }
                ],
                "index": 0,
                "category": "Fey"
            }
        ],
        "pointsPerCategory": {
            "Characters": 1155,
            "Core": 1025,
            "Special": 1395,
            "Total": 4000
        },
        "magicalness": 8,
        "modelCount": {
            "characters": 3,
            "height0": 0,
            "height1": 30,
            "height2": 30,
            "height3": 1,
            "height4": 1,
            "height5": 0,
            "total": 65
        },
        "unitCount": {
            "characters": 3,
            "singleModel": 2,
            "rankAndFile": 5,
            "total": 10
        }
    },
    "armyListTwo": {
        "units": [
            {
                "name": "Sanctioned Warlock",
                "cost": 480,
                "options": [
                    {
                        "name": "General",
                        "type": "Leadership"
                    },
                    {
                        "name": "Light Troops",
                        "type": "Mount"
                    },
                    {
                        "name": "Wizard Master",
                        "type": "Wizard Level"
                    },
                    {
                        "name": "Evocation",
                        "type": "Path"
                    },
                    {
                        "name": "Mimic Cloak",
                        "type": "Magic Items"
                    }
                ],
                "index": 0,
                "category": "Characters"
            },
            {
                "name": "Temple Exarch",
                "cost": 310,
                "options": [
                    {
                        "name": "Wizard Adept",
                        "type": "Wizard Level"
                    },
                    {
                        "name": "Paired Weapons",
                        "type": "Melee Weapons"
                    },
                    {
                        "name": "Divination",
                        "type": "Path"
                    }
                ],
                "index": 0,
                "category": "Characters"
            },
            {
                "name": "Silexian Spears",
                "cost": 497,
                "options": [
                    {
                        "name": "Sheltering Standard",
                        "type": "Magic Items"
                    },
                    {
                        "name": "Standard Bearer",
                        "type": "Command Group"
                    },
                    {
                        "name": "Musician",
                        "type": "Command Group"
                    }
                ],
                "index": 0,
                "models": 33,
                "category": "Core"
            },
            {
                "name": "Temple Militants",
                "cost": 350,
                "options": [
                    {
                        "name": "Stalker's Standard",
                        "type": "Magic Items"
                    },
                    {
                        "name": "Standard Bearer",
                        "type": "Command Group"
                    },
                    {
                        "name": "Musician",
                        "type": "Command Group"
                    }
                ],
                "index": 0,
                "models": 20,
                "category": "Core"
            },
            {
                "name": "Shadow Riders",
                "cost": 190,
                "options": [
                    {
                        "name": "Light Lance",
                        "type": "Melee Weapons"
                    }
                ],
                "index": 0,
                "models": 5,
                "category": "Core"
            },
            {
                "name": "Dread Knights",
                "cost": 354,
                "options": [
                    {
                        "name": "Banner of Urlain",
                        "type": "Magic Items"
                    },
                    {
                        "name": "Standard Bearer",
                        "type": "Command Group"
                    },
                    {
                        "name": "Lance",
                        "type": "Melee Weapons"
                    }
                ],
                "index": 0,
                "models": 6,
                "category": "Special"
            },
            {
                "name": "Dread Knights",
                "cost": 354,
                "options": [
                    {
                        "name": "Banner of Urlain",
                        "type": "Magic Items"
                    },
                    {
                        "name": "Standard Bearer",
                        "type": "Command Group"
                    },
                    {
                        "name": "Lance",
                        "type": "Melee Weapons"
                    }
                ],
                "index": 1,
                "models": 6,
                "category": "Special"
            },
            {
                "name": "Dread Acolytes",
                "cost": 252,
                "options": [
                    {
                        "name": "Musician",
                        "type": "Command Group"
                    },
                    {
                        "name": "Temple Acolytes",
                        "type": "Other"
                    }
                ],
                "index": 0,
                "models": 6,
                "category": "Special"
            },
            {
                "name": "Dread Acolytes",
                "cost": 252,
                "options": [
                    {
                        "name": "Musician",
                        "type": "Command Group"
                    },
                    {
                        "name": "Temple Acolytes",
                        "type": "Other"
                    }
                ],
                "index": 1,
                "models": 6,
                "category": "Special"
            },
            {
                "name": "Divine Altar",
                "cost": 240,
                "options": [
                    {
                        "name": "Altar of Nabh",
                        "type": "Other"
                    }
                ],
                "index": 0,
                "category": "Special"
            },
            {
                "name": "Gorgons",
                "cost": 210,
                "options": [
                    {
                        "name": "Paired Weapons",
                        "type": "Melee Weapons"
                    }
                ],
                "index": 0,
                "models": 2,
                "category": "Special"
            },
            {
                "name": "Gorgons",
                "cost": 210,
                "options": [
                    {
                        "name": "Paired Weapons",
                        "type": "Melee Weapons"
                    }
                ],
                "index": 1,
                "models": 2,
                "category": "Special"
            },
            {
                "name": "Black Cloaks",
                "cost": 150,
                "options": [
                    {
                        "name": "Repeater Crossbow",
                        "type": "Shooting Weapons"
                    },
                    {
                        "name": "Covert Operatives",
                        "type": "Other"
                    }
                ],
                "index": 0,
                "models": 5,
                "category": "Special"
            },
            {
                "name": "Black Cloaks",
                "cost": 150,
                "options": [
                    {
                        "name": "Repeater Crossbow",
                        "type": "Shooting Weapons"
                    },
                    {
                        "name": "Covert Operatives",
                        "type": "Other"
                    }
                ],
                "index": 1,
                "models": 5,
                "category": "Special"
            }
        ],
        "pointsPerCategory": {
            "Characters": 790,
            "Core": 1037,
            "Special": 2172,
            "Total": 3999
        },
        "magicalness": 11,
        "modelCount": {
            "characters": 2,
            "height0": 0,
            "height1": 63,
            "height2": 29,
            "height3": 4,
            "height4": 0,
            "height5": 1,
            "total": 99
        },
        "unitCount": {
            "characters": 2,
            "singleModel": 1,
            "rankAndFile": 11,
            "total": 14
        }
    }
}